indiapins/__init__.py
indiapins/cli.py
indiapins/indiapins.py
indiapins/pins.json.bz2
indiapins-1.0.4.dist-info/AUTHORS.rst
indiapins-1.0.4.dist-info/LICENSE
indiapins-1.0.4.dist-info/METADATA
indiapins-1.0.4.dist-info/WHEEL
indiapins-1.0.4.dist-info/entry_points.txt
indiapins-1.0.4.dist-info/top_level.txt
indiapins-1.0.4.dist-info/RECORD
